AIS_Oversampler/ArtificialImmuneSystem.py
AIS_Oversampler/__init__.py
AIS_Oversampler-1.0.dist-info/LICENSE
AIS_Oversampler-1.0.dist-info/METADATA
AIS_Oversampler-1.0.dist-info/WHEEL
AIS_Oversampler-1.0.dist-info/top_level.txt
AIS_Oversampler-1.0.dist-info/RECORD
