Metadata-Version: 2.1
Name: AIS-Oversampler
Version: 1.0
Summary: ML Oversampler for binary classification tasks based on Artificial Immune Systems
Home-page: https://github.com/nikhil815/Artificial-Immune-System-For-Class-Imbalance
Author: nikhil815
Author-email: pyndiah.nikhil@gmail.com
Project-URL: Bug Tracker, https://github.com/nikhil815/Artificial-Immune-System-For-Class-Imbalance/issues
Classifier: Programming Language :: Python :: 3
Classifier: License :: OSI Approved :: MIT License
Classifier: Operating System :: OS Independent
Requires-Python: >=3
License-File: LICENSE
